surrortg/__init__.py
surrortg/config_parser.py
surrortg/game.py
surrortg/game_io.py
surrortg/devices/__init__.py
surrortg/devices/udp/__init__.py
surrortg/devices/udp/udp_actuator.py
surrortg/devices/udp/udp_bot.py
surrortg/devices/udp/udp_car.py
surrortg/devices/udp/udp_input.py
surrortg/devices/udp/udp_protocol.py
surrortg/image_recognition/__init__.py
surrortg/image_recognition/async_video_capture.py
surrortg/image_recognition/pixel_detect.py
surrortg/inputs/__init__.py
surrortg/inputs/delayed_switch.py
surrortg/inputs/input.py
surrortg/inputs/joystick.py
surrortg/inputs/linear_actuator.py
surrortg/inputs/switch.py
surrortg/inputs/input_filters/__init__.py
surrortg/inputs/input_filters/spam_filter.py
surrortg/network/__init__.py
surrortg/network/ge_api_client.py
surrortg/network/message_router.py
surrortg/network/socket_handler.py
surrortg/utils/__init__.py
surrortg/utils/obs_scene_switcher.py
surrortg-0.2.2a2.dist-info/LICENSE
surrortg-0.2.2a2.dist-info/WHEEL
surrortg-0.2.2a2.dist-info/METADATA
surrortg-0.2.2a2.dist-info/RECORD
