Metadata-Version: 2.1
Name: surrortg
Version: 0.2.2a2
Summary: surrortg
Home-page: https://github.com/SurrogateInc/surrortgsdk-sdk
Author: Surrogate Inc
Classifier: License :: OSI Approved :: MIT License
Requires-Dist: aiohttp==3.7.4
Requires-Dist: async-timeout==3.0.1
Requires-Dist: attrs==20.3.0
Requires-Dist: chardet==3.0.4
Requires-Dist: idna==2.10
Requires-Dist: multidict==5.1.0
Requires-Dist: pigpio==1.78
Requires-Dist: python-engineio==3.14.2
Requires-Dist: python-socketio==4.6.1
Requires-Dist: pyyaml==5.4.1
Requires-Dist: six==1.15.0
Requires-Dist: toml==0.10.2
Requires-Dist: typing-extensions==3.7.4.3
Requires-Dist: yarl==1.6.3
Requires-Dist: alabaster==0.7.12 ; extra == "dev"
Requires-Dist: appdirs==1.4.4 ; extra == "dev"
Requires-Dist: attrs==20.3.0 ; extra == "dev"
Requires-Dist: babel==2.9.0 ; extra == "dev"
Requires-Dist: black==20.8b1 ; extra == "dev"
Requires-Dist: certifi==2020.12.5 ; extra == "dev"
Requires-Dist: cfgv==3.2.0 ; extra == "dev"
Requires-Dist: chardet==3.0.4 ; extra == "dev"
Requires-Dist: click==7.1.2 ; extra == "dev"
Requires-Dist: codespell==v2.0.0 ; extra == "dev"
Requires-Dist: commonmark==0.9.1 ; extra == "dev"
Requires-Dist: distlib==0.3.1 ; extra == "dev"
Requires-Dist: docutils==0.16 ; extra == "dev"
Requires-Dist: filelock==3.0.12 ; extra == "dev"
Requires-Dist: flake8-polyfill==1.0.2 ; extra == "dev"
Requires-Dist: flake8==3.9.0 ; extra == "dev"
Requires-Dist: identify==2.2.2 ; extra == "dev"
Requires-Dist: idna==2.10 ; extra == "dev"
Requires-Dist: imagesize==1.2.0 ; extra == "dev"
Requires-Dist: importlib-metadata==3.10.0 ; extra == "dev"
Requires-Dist: isort==5.7.0 ; extra == "dev"
Requires-Dist: jinja2==2.11.3 ; extra == "dev"
Requires-Dist: markdown-it-py==0.6.2 ; extra == "dev"
Requires-Dist: markupsafe==1.1.1 ; extra == "dev"
Requires-Dist: mccabe==0.6.1 ; extra == "dev"
Requires-Dist: mdit-py-plugins==0.2.6 ; extra == "dev"
Requires-Dist: mypy-extensions==0.4.3 ; extra == "dev"
Requires-Dist: myst-parser==0.13.5 ; extra == "dev"
Requires-Dist: packaging==20.9 ; extra == "dev"
Requires-Dist: pathspec==0.8.1 ; extra == "dev"
Requires-Dist: pep517==0.10.0 ; extra == "dev"
Requires-Dist: pep8-naming==0.11.1 ; extra == "dev"
Requires-Dist: pip-tools==6.0.1 ; extra == "dev"
Requires-Dist: pre-commit==2.11.1 ; extra == "dev"
Requires-Dist: pycodestyle==2.7.0 ; extra == "dev"
Requires-Dist: pyflakes==2.3.1 ; extra == "dev"
Requires-Dist: pygments==2.8.1 ; extra == "dev"
Requires-Dist: pyparsing==2.4.7 ; extra == "dev"
Requires-Dist: pytz==2021.1 ; extra == "dev"
Requires-Dist: pyyaml==5.4.1 ; extra == "dev"
Requires-Dist: recommonmark==0.6.0 ; extra == "dev"
Requires-Dist: regex==2021.3.17 ; extra == "dev"
Requires-Dist: requests==2.25.1 ; extra == "dev"
Requires-Dist: six==1.15.0 ; extra == "dev"
Requires-Dist: snowballstemmer==2.1.0 ; extra == "dev"
Requires-Dist: sphinx-rtd-theme==0.4.3 ; extra == "dev"
Requires-Dist: sphinx==3.1.1 ; extra == "dev"
Requires-Dist: sphinxcontrib-applehelp==1.0.2 ; extra == "dev"
Requires-Dist: sphinxcontrib-devhelp==1.0.2 ; extra == "dev"
Requires-Dist: sphinxcontrib-htmlhelp==1.0.3 ; extra == "dev"
Requires-Dist: sphinxcontrib-jsmath==1.0.1 ; extra == "dev"
Requires-Dist: sphinxcontrib-qthelp==1.0.3 ; extra == "dev"
Requires-Dist: sphinxcontrib-serializinghtml==1.1.4 ; extra == "dev"
Requires-Dist: toml==0.10.2 ; extra == "dev"
Requires-Dist: typed-ast==1.4.2 ; extra == "dev"
Requires-Dist: typing-extensions==3.7.4.3 ; extra == "dev"
Requires-Dist: urllib3==1.26.4 ; extra == "dev"
Requires-Dist: virtualenv==20.4.3 ; extra == "dev"
Requires-Dist: zipp==3.4.1 ; extra == "dev"
Provides-Extra: dev
